bidnlp/__init__.py
bidnlp/classification/__init__.py
bidnlp/classification/base_classifier.py
bidnlp/classification/feature_extraction.py
bidnlp/classification/keyword_classifier.py
bidnlp/classification/sentiment_analyzer.py
bidnlp/lemmatization/__init__.py
bidnlp/lemmatization/persian_lemmatizer.py
bidnlp/pos/__init__.py
bidnlp/pos/base_tagger.py
bidnlp/pos/hmm_tagger.py
bidnlp/pos/pos_tags.py
bidnlp/pos/rule_based_tagger.py
bidnlp/preprocessing/__init__.py
bidnlp/preprocessing/cleaner.py
bidnlp/preprocessing/normalizer.py
bidnlp/preprocessing/number_normalizer.py
bidnlp/preprocessing/punctuation.py
bidnlp/stemming/__init__.py
bidnlp/stemming/persian_stemmer.py
bidnlp/tokenization/__init__.py
bidnlp/tokenization/sentence_tokenizer.py
bidnlp/tokenization/subword_tokenizer.py
bidnlp/tokenization/word_tokenizer.py
bidnlp/utils/__init__.py
bidnlp/utils/characters.py
bidnlp/utils/metrics.py
bidnlp/utils/statistics.py
bidnlp/utils/stopwords.py
bidnlp/utils/validators.py
bidnlp-0.2.2.dist-info/licenses/LICENSE
bidnlp-0.2.2.dist-info/METADATA
bidnlp-0.2.2.dist-info/WHEEL
bidnlp-0.2.2.dist-info/top_level.txt
bidnlp-0.2.2.dist-info/RECORD
