Metadata-Version: 2.4
Name: bidnlp
Version: 0.2.2
Summary: A Comprehensive Persian (Farsi) Natural Language Processing Library
Author-email: Aghabidareh <aghabidareh@example.com>
Maintainer-email: Aghabidareh <aghabidareh@example.com>
License: MIT
Project-URL: Homepage, https://github.com/aghabidareh/bidnlp
Project-URL: Documentation, https://github.com/aghabidareh/bidnlp
Project-URL: Repository, https://github.com/aghabidareh/bidnlp
Project-URL: Issues, https://github.com/aghabidareh/bidnlp/issues
Project-URL: Changelog, https://github.com/aghabidareh/bidnlp/releases
Keywords: nlp,persian,farsi,natural-language-processing,text-processing,tokenization,preprocessing,stemming,lemmatization,sentiment-analysis,persian-nlp
Classifier: Development Status :: 4 - Beta
Classifier: Intended Audience :: Developers
Classifier: Intended Audience :: Science/Research
Classifier: License :: OSI Approved :: MIT License
Classifier: Operating System :: OS Independent
Classifier: Programming Language :: Python :: 3
Classifier: Programming Language :: Python :: 3.7
Classifier: Programming Language :: Python :: 3.8
Classifier: Programming Language :: Python :: 3.9
Classifier: Programming Language :: Python :: 3.10
Classifier: Programming Language :: Python :: 3.11
Classifier: Programming Language :: Python :: 3.12
Classifier: Topic :: Scientific/Engineering :: Artificial Intelligence
Classifier: Topic :: Software Development :: Libraries :: Python Modules
Classifier: Topic :: Text Processing :: Linguistic
Requires-Python: >=3.7
License-File: LICENSE
Provides-Extra: dev
Requires-Dist: pytest>=7.0; extra == "dev"
Requires-Dist: pytest-cov>=4.0; extra == "dev"
Requires-Dist: pytest-xdist>=3.0; extra == "dev"
Requires-Dist: black>=23.0; extra == "dev"
Requires-Dist: isort>=5.12; extra == "dev"
Requires-Dist: flake8>=6.0; extra == "dev"
Requires-Dist: mypy>=1.0; extra == "dev"
Requires-Dist: pylint>=2.17; extra == "dev"
Requires-Dist: safety>=2.3; extra == "dev"
Requires-Dist: bandit>=1.7; extra == "dev"
Dynamic: license-file
